encryption_cli/__init__.py
encryption_cli/main.py
encryption_cli-0.1.0.dist-info/licenses/LICENSE
encryption_cli-0.1.0.dist-info/METADATA
encryption_cli-0.1.0.dist-info/WHEEL
encryption_cli-0.1.0.dist-info/entry_points.txt
encryption_cli-0.1.0.dist-info/top_level.txt
encryption_cli-0.1.0.dist-info/RECORD
