Metadata-Version: 2.4
Name: encryption_cli
Version: 0.1.0
Summary: A cli tool for file encryption
Author-email: Franek Kurzawa <me@franektoube.pl>
License-Expression: MIT
Keywords: file-encryption,encryption,files
Classifier: Development Status :: 3 - Alpha
Classifier: Environment :: Console
Classifier: Operating System :: MacOS
Classifier: Operating System :: Microsoft :: Windows
Classifier: Operating System :: POSIX :: Linux
Classifier: Programming Language :: Python
Classifier: Programming Language :: Python :: 3.8
Requires-Python: >=3.8
License-File: LICENSE
Requires-Dist: cryptography==46.0.3
Requires-Dist: InquirerPy==0.3.4
Requires-Dist: rich==14.2.0
Dynamic: license-file
